<products>	
	<product>
		<name>Jacket</name>
		<category>clothing</category>
		<price>130</price>
	</product>
	<product>
		<name>Suit Blazer</name>
		<category>clothing</category>
		<price>63</price>
	</product>
	<product>
		<name>Cardigan</name>
		<category>clothing</category>
		<price>25</price>
	</product>
	<product>
		<name>Dress</name>
		<category>clothing</category>
		<price>49</price>
	</product>
	<product>
		<name>Lisinopril</name>
		<category>prescriptiondrug</category>
		<price>7.66</price>
	</product>
	<product>
		<name>Hydrochlorothiazide</name>
		<category>prescriptiondrug</category>
		<price>8.45</price>
	</product>
	<product>
		<name>Azithromycin</name>
		<category>prescriptiondrug</category>
		<price>9.89</price>
	</product>
	<product>
		<name>Amoxicillin</name>
		<category>prescriptiondrug</category>
		<price>5.65</price>
	</product>
	<product>
		<name>Synthroid</name>
		<category>prescriptiondrug</category>
		<price>37.99</price>
	</product>
	<product>
		<name>Advil</name>
		<category>nonprescriptiondrug</category>
		<price>8.98</price>
	</product>
	<product>
		<name>Motrin</name>
		<category>nonprescriptiondrug</category>
		<price>12.96</price>
	</product>
	<product>
		<name>Aleve</name>
		<category>nonprescriptiondrug</category>
		<price>14.92</price>
	</product>
	<product>
		<name>Colace</name>
		<category>nonprescriptiondrug</category>
		<price>13.97</price>
	</product>
	<product>
		<name>Pizza</name>
		<category>preparedfood</category>
		<price>2.98</price>
	</product>
	<product>
		<name>Beef Jerky</name>
		<category>preparedfood</category>
		<price>22.51</price>
	</product>
	<product>
		<name>Noodle soup</name>
		<category>preparedfood</category>
		<price>0.98</price>
	</product>
	<product>
		<name>Eggs</name>
		<category>groceries</category>
		<price>1.6</price>
	</product>
	<product>
		<name>Bananas</name>
		<category>groceries</category>
		<price>0.6</price>
	</product>
	<product>
		<name>Cherry</name>
		<category>groceries</category>
		<price>3.4</price>
	</product>
</products>
